minifind/__init__.py
minifind-0.0.3.dist-info/LICENSE
minifind-0.0.3.dist-info/METADATA
minifind-0.0.3.dist-info/WHEEL
minifind-0.0.3.dist-info/top_level.txt
minifind-0.0.3.dist-info/RECORD
