Metadata-Version: 2.1
Name: minifind
Version: 0.0.3
Summary: os.walk wrapper with predicates
Home-page: https://github.com/mugiseyebrows/minifind
Author: Stanislav Doronin
Author-email: mugisbrows@gmail.com
License-File: LICENSE
